dynatrace_extension/__about__.py
dynatrace_extension/__init__.py
dynatrace_extension/cli/__init__.py
dynatrace_extension/cli/main.py
dynatrace_extension/cli/schema.py
dynatrace_extension/cli/create/__init__.py
dynatrace_extension/cli/create/create.py
dynatrace_extension/cli/create/extension_template/.gitignore.template
dynatrace_extension/cli/create/extension_template/README.md.template
dynatrace_extension/cli/create/extension_template/activation.json.template
dynatrace_extension/cli/create/extension_template/ruff.toml.template
dynatrace_extension/cli/create/extension_template/secrets.json.template
dynatrace_extension/cli/create/extension_template/setup.py.template
dynatrace_extension/cli/create/extension_template/extension/activationSchema.json.template
dynatrace_extension/cli/create/extension_template/extension/extension.yaml.template
dynatrace_extension/cli/create/extension_template/extension_name/__init__.py.template
dynatrace_extension/cli/create/extension_template/extension_name/__main__.py.template
dynatrace_extension/sdk/__init__.py
dynatrace_extension/sdk/activation.py
dynatrace_extension/sdk/callback.py
dynatrace_extension/sdk/communication.py
dynatrace_extension/sdk/event.py
dynatrace_extension/sdk/extension.py
dynatrace_extension/sdk/helper.py
dynatrace_extension/sdk/metric.py
dynatrace_extension/sdk/runtime.py
dynatrace_extension/sdk/snapshot.py
dynatrace_extension/sdk/status.py
dynatrace_extension/sdk/throttled_logger.py
dynatrace_extension/sdk/vendor/__init__.py
dynatrace_extension/sdk/vendor/mureq/LICENSE
dynatrace_extension/sdk/vendor/mureq/__init__.py
dynatrace_extension/sdk/vendor/mureq/mureq.py
dt_extensions_sdk-1.7.4.dist-info/METADATA
dt_extensions_sdk-1.7.4.dist-info/WHEEL
dt_extensions_sdk-1.7.4.dist-info/entry_points.txt
dt_extensions_sdk-1.7.4.dist-info/licenses/LICENSE.txt
dt_extensions_sdk-1.7.4.dist-info/RECORD
