Metadata-Version: 2.4
Name: dt-extensions-sdk
Version: 1.7.4
Project-URL: Documentation, https://github.com/dynatrace-extensions/dt-extensions-python-sdk#readme
Project-URL: Issues, https://github.com/dynatrace-extensions/dt-extensions-python-sdk/issues
Project-URL: Source, https://github.com/dynatrace-extensions/dt-extensions-python-sdk
Author-email: dlopes7 <davidribeirolopes@gmail.com>
License-Expression: MIT
License-File: LICENSE.txt
Classifier: Development Status :: 4 - Beta
Classifier: Programming Language :: Python
Classifier: Programming Language :: Python :: 3.10
Classifier: Programming Language :: Python :: Implementation :: CPython
Classifier: Programming Language :: Python :: Implementation :: PyPy
Requires-Python: <3.11,>=3.10
Provides-Extra: cli
Requires-Dist: dt-cli>=1.6.13; extra == 'cli'
Requires-Dist: pyyaml; extra == 'cli'
Requires-Dist: ruff; extra == 'cli'
Requires-Dist: typer[all]; extra == 'cli'
